README.rst
setup.py
src/birding/__init__.py
src/birding/bolt.py
src/birding/config.py
src/birding/follow.py
src/birding/gnip.py
src/birding/search.py
src/birding/shelf.py
src/birding/spout.py
src/birding/twitter.py
src/birding/version.py
src/birding.egg-info/PKG-INFO
src/birding.egg-info/SOURCES.txt
src/birding.egg-info/dependency_links.txt
src/birding.egg-info/entry_points.txt
src/birding.egg-info/not-zip-safe
src/birding.egg-info/requires.txt
src/birding.egg-info/top_level.txt