Metadata-Version: 1.0
Name: birding
Version: 0.2.1
Summary: Stream twitter searches using the public API.
Home-page: https://github.com/Parsely/birding
Author: Parsely, Inc.
Author-email: hello@parsely.com
License: Apache License 2.0
Platform: UNKNOWN
